fancy_einsum/__init__.py
fancy_einsum/test_convert_equation.py
fancy_einsum/test_numpy.py
fancy_einsum/test_torch.py
fancy_einsum-0.0.3.dist-info/LICENSE
fancy_einsum-0.0.3.dist-info/METADATA
fancy_einsum-0.0.3.dist-info/WHEEL
fancy_einsum-0.0.3.dist-info/top_level.txt
fancy_einsum-0.0.3.dist-info/RECORD
