Metadata-Version: 2.1
Name: fancy_einsum
Version: 0.0.3
Summary: Drop-in replacement for torch/numpy einsum, with descriptive variable names in equations
Home-page: https://github.com/Kiv/fancy_einsum
Author: Chris MacLeod
Author-email: chrism6794@gmail.com
License: MIT
Project-URL: Bug Tracker, https://github.com/Kiv/fancy_einsum/issues
Platform: UNKNOWN
Classifier: Programming Language :: Python :: 3
Classifier: License :: OSI Approved :: MIT License
Classifier: Operating System :: OS Independent
Requires-Python: >=3.6
License-File: LICENSE
